{
  "$schema": "http://json-schema.org/draft-07/schema#",
  "$id": "https://github.com/AdarGit008/baseline-skill/schema/record.claim.schema.json",
  "title": "claim record — records/claims/CLM-NNNN.json",
  "description": "One external claim, one owned file (C23/C17) — exploded from the V1 docs/CLAIMS.json monolith by `gen migrate-claims` (M4c; the legacy monolith\u2019s checker read retired at the M7 contraction). Field semantics are V1's, adversarially earned: statement + type + build_state + blast_radius always; existential claims need a de_risk_milestone; novelty/competitive/market claims need prior_art_checked + how_we_differ (those conditionals are enforced by the CLAIM rules, which activate at descriptor maturity 'claimed' — this schema binds shape, not applicability).",
  "type": "object",
  "additionalProperties": false,
  "required": ["record", "id", "statement", "type", "build_state", "blast_radius"],
  "properties": {
    "record": {
      "type": "string",
      "enum": ["claim/1"],
      "description": "Record kind + schema version."
    },
    "id": {
      "type": "string",
      "pattern": "^CLM-[0-9]{4}$",
      "description": "The record's identity — must match the filename."
    },
    "slug": {
      "type": "string",
      "description": "The V1 register id (e.g. 'wedge-migration'), preserved by gen migrate-claims so cross-references survive the explosion."
    },
    "statement": {
      "type": "string",
      "minLength": 1,
      "description": "The claim itself, as asserted to the outside world."
    },
    "type": {
      "type": "string",
      "enum": ["technical", "novelty", "competitive", "market", "empirical", "security"],
      "description": "Claim species — drives which CLAIM rules apply."
    },
    "build_state": {
      "type": "string",
      "enum": ["shipped-tested", "designed-unshipped", "assumed-unmeasured"],
      "description": "How real the claim is right now."
    },
    "blast_radius": {
      "type": "string",
      "enum": ["existential", "recoverable"],
      "description": "What it costs if the claim is wrong."
    },
    "de_risk_milestone": {
      "type": "string",
      "description": "For existential claims: the concrete step that converts assumption into evidence."
    },
    "prior_art_checked": {
      "type": "string",
      "pattern": "^[0-9]{4}-[0-9]{2}-[0-9]{2}$",
      "description": "When the prior-art sweep was last done (novelty/competitive/market claims; CLAIM-04 staleness reads this)."
    },
    "how_we_differ": {
      "type": "string",
      "description": "The differentiation argument (novelty/competitive/market claims)."
    },
    "confidence": {
      "type": "string",
      "enum": ["low", "medium", "high"],
      "description": "Honest confidence in the claim as stated."
    },
    "citations": {
      "type": "array",
      "description": "Evidence: each citation must say what it supports and why (CLAIM-06).",
      "items": {
        "type": "object",
        "additionalProperties": false,
        "required": ["url", "supports_because"],
        "properties": {
          "url": { "type": "string", "minLength": 1 },
          "supports_because": { "type": "string", "minLength": 1, "description": "Why this source supports the claim — a bare link is not evidence." }
        }
      }
    }
  }
}
